python_package_demo/__init__.py
python_package_demo/demo.py
demo_shiva-0.0.1.dist-info/LICENSE
demo_shiva-0.0.1.dist-info/METADATA
demo_shiva-0.0.1.dist-info/WHEEL
demo_shiva-0.0.1.dist-info/top_level.txt
demo_shiva-0.0.1.dist-info/RECORD
